froyo/__init__.py
froyo-1.1.0.dist-info/METADATA
froyo-1.1.0.dist-info/RECORD
froyo-1.1.0.dist-info/WHEEL
froyo-1.1.0.dist-info/entry_points.txt
froyo-1.1.0.dist-info/top_level.txt
